prometheus_ml/__init__.py
prometheus_ml/cli.py
prometheus_ml/prometheus_ml.py
prometheus_ml-0.1.0.dist-info/METADATA
prometheus_ml-0.1.0.dist-info/RECORD
prometheus_ml-0.1.0.dist-info/WHEEL
prometheus_ml-0.1.0.dist-info/entry_points.txt
prometheus_ml-0.1.0.dist-info/top_level.txt
