Metadata-Version: 2.1
Name: prometheus-ml
Version: 0.1.0
Summary: Machine Learning Framework, standing on the shoulders of TITANS 
Home-page: https://github.com/netzkontrast/prometheus_ml
Author: Michael Schimmer
Author-email: michael@nettkontrast.de
License: MIT license
Keywords: prometheus_ml
Platform: UNKNOWN
Classifier: Development Status :: 2 - Pre-Alpha
Classifier: Intended Audience :: Developers
Classifier: License :: OSI Approved :: MIT License
Classifier: Natural Language :: English
Classifier: Programming Language :: Python :: 3.5
Requires-Dist: Click (>=6.0)
